{
  "user_id": "AHSLMK4MF77OSOQEEYD5D5NV4SMA",
  "core_patterns": {
    "genre_preference": {
      "value": "mixed",
      "evidence": [
        "No specific genre preferences identified."
      ],
      "confidence": 0.2,
      "polarity": "mixed",
      "transferability_hint": "low"
    },
    "narrative_complexity": {
      "value": "simple",
      "evidence": [
        "No complex narratives mentioned."
      ],
      "confidence": 0.2,
      "polarity": "mixed",
      "transferability_hint": "low"
    },
    "pacing_preference": {
      "value": "mixed",
      "evidence": [
        "No specific pacing preferences identified."
      ],
      "confidence": 0.2,
      "polarity": "mixed",
      "transferability_hint": "low"
    },
    "quality_sensitivity": {
      "value": "high",
      "evidence": [
        "Item arrived not the quality as described.",
        "Dvd froze in parts."
      ],
      "confidence": 0.8,
      "polarity": "negative",
      "transferability_hint": "medium"
    },
    "brand_loyalty": {
      "value": "low",
      "evidence": [
        "No mentions of specific creators or franchises."
      ],
      "confidence": 0.2,
      "polarity": "mixed",
      "transferability_hint": "low"
    },
    "sensory_preference": {
      "value": "low",
      "evidence": [
        "No sensory experiences mentioned."
      ],
      "confidence": 0.2,
      "polarity": "mixed",
      "transferability_hint": "low"
    },
    "emotional_resonance": {
      "value": "low",
      "evidence": [
        "No emotional impact mentioned."
      ],
      "confidence": 0.2,
      "polarity": "mixed",
      "transferability_hint": "low"
    }
  },
  "additional_patterns": [],
  "summary": "The user has shown a strong sensitivity to quality, often expressing dissatisfaction with items that do not meet expectations. However, there is a lack of specific genre preferences, narrative complexity, or emotional engagement in their reviews."
}