{
  "user_id": "AH5H2GLTYV3IZM7XXNTOLP6UJZCQ",
  "core_patterns": {
    "genre_preference": {
      "value": "mixed",
      "evidence": [
        "One of my favorites!!",
        "Really liked it"
      ],
      "confidence": 0.3,
      "polarity": "mixed",
      "transferability_hint": "medium"
    },
    "narrative_complexity": {
      "value": "simple",
      "evidence": [
        "Loved it!!!",
        "Always good"
      ],
      "confidence": 0.2,
      "polarity": "mixed",
      "transferability_hint": "low"
    },
    "pacing_preference": {
      "value": "fast",
      "evidence": [
        "Loved it. It was so funny.",
        "Would definitely recommend"
      ],
      "confidence": 0.3,
      "polarity": "positive",
      "transferability_hint": "medium"
    },
    "quality_sensitivity": {
      "value": "low",
      "evidence": [
        "Not the best, but not the worst.",
        "Pretty good."
      ],
      "confidence": 0.3,
      "polarity": "mixed",
      "transferability_hint": "medium"
    },
    "brand_loyalty": {
      "value": "low",
      "evidence": [
        "Always a favorite",
        "Love it"
      ],
      "confidence": 0.2,
      "polarity": "mixed",
      "transferability_hint": "low"
    },
    "sensory_preference": {
      "value": "high",
      "evidence": [
        "Great book, great show",
        "Loved it!!!"
      ],
      "confidence": 0.4,
      "polarity": "positive",
      "transferability_hint": "high"
    },
    "emotional_resonance": {
      "value": "high",
      "evidence": [
        "Loved it!!!",
        "One of my favorites"
      ],
      "confidence": 0.5,
      "polarity": "positive",
      "transferability_hint": "high"
    }
  },
  "additional_patterns": [],
  "summary": "The user has a strong preference for enjoyable and entertaining content, often expressing love for what they watch. They seem to favor fast-paced narratives with high emotional resonance, while showing less concern for production quality and specific creators."
}