{
  "user_id": "AFNHP3FB663SN5QAK6KK27YMSTMA",
  "core_patterns": {
    "genre_preference": {
      "value": "comedy, drama, action, western",
      "evidence": [
        "\"One of the funniest sitcoms since the 60'. Not for kids.\"",
        "\"I love westerns and this was one of the best in years.\""
      ],
      "confidence": 0.8,
      "polarity": "positive",
      "transferability_hint": "medium"
    },
    "narrative_complexity": {
      "value": "simple",
      "evidence": [
        "\"Was nothing like the others. Slow moving and very bad script.\"",
        "\"Started a bit slow but became a good movie.\""
      ],
      "confidence": 0.6,
      "polarity": "mixed",
      "transferability_hint": "medium"
    },
    "pacing_preference": {
      "value": "slow",
      "evidence": [
        "\"Slow moving and very bad script.\"",
        "\"To slow and old.\""
      ],
      "confidence": 0.7,
      "polarity": "negative",
      "transferability_hint": "medium"
    },
    "quality_sensitivity": {
      "value": "low",
      "evidence": [
        "\"Even the effects were not as good.\"",
        "\"I was very disappointed and sicken by this movie.\""
      ],
      "confidence": 0.5,
      "polarity": "mixed",
      "transferability_hint": "medium"
    },
    "brand_loyalty": {
      "value": "NCIS, JAG",
      "evidence": [
        "\"Best show on TV. We own every season even the 2 that where on the 8th. season of JAG.\"",
        "\"Still the best show on TV.\""
      ],
      "confidence": 0.9,
      "polarity": "positive",
      "transferability_hint": "high"
    },
    "sensory_preference": {
      "value": "visual effects",
      "evidence": [
        "\"Very good effects in the blu ray.\"",
        "\"Great cases. One of the funniest sitcoms since the 60'.\""
      ],
      "confidence": 0.6,
      "polarity": "positive",
      "transferability_hint": "medium"
    },
    "emotional_resonance": {
      "value": "high",
      "evidence": [
        "\"This is a timeless movie and one of touching heart.\"",
        "\"It is a movie that brings out the fears of commitment and being yourself.\""
      ],
      "confidence": 0.8,
      "polarity": "positive",
      "transferability_hint": "high"
    }
  },
  "additional_patterns": [],
  "summary": "The user enjoys comedies and dramas, particularly those with strong visual effects and emotional resonance. They show a preference for slower-paced narratives but express disappointment with poor scripts and production quality."
}