{
  "user_id": "AEL3SJX2ADGYSONZPPHZ7UYDR5OA",
  "core_patterns": {
    "genre_preference": {
      "value": "classic TV shows, crime, family drama",
      "evidence": [
        "Love this entire original series.",
        "Loved this show - hated when they killed off James the father."
      ],
      "confidence": 0.8,
      "polarity": "positive",
      "transferability_hint": "medium"
    },
    "narrative_complexity": {
      "value": "simple",
      "evidence": [
        "Enjoyable - well directed and great score by Tangerine Dream",
        "A very enjoyable well made movie - with great cast of characters."
      ],
      "confidence": 0.7,
      "polarity": "positive",
      "transferability_hint": "high"
    },
    "pacing_preference": {
      "value": "slow",
      "evidence": [
        "Some episodes sink - while others still have classic and important messages - of never give up.",
        "Enjoyable - as most cast (with the exception of Tina/Ginger and Dawn/Mary Ann) return."
      ],
      "confidence": 0.6,
      "polarity": "positive",
      "transferability_hint": "medium"
    },
    "quality_sensitivity": {
      "value": "low",
      "evidence": [
        "cheap effects - but a guilty pleasure",
        "Enjoyable - well directed and great score by Tangerine Dream"
      ],
      "confidence": 0.5,
      "polarity": "mixed",
      "transferability_hint": "medium"
    },
    "brand_loyalty": {
      "value": "high",
      "evidence": [
        "I wished they never stopped making Columbo (and Mrs. Columbo) movies / series.",
        "Best Hawaii Five-O is the original series."
      ],
      "confidence": 0.9,
      "polarity": "positive",
      "transferability_hint": "high"
    },
    "sensory_preference": {
      "value": "atmospheric music, character-driven storytelling",
      "evidence": [
        "great score by Tangerine Dream",
        "Enjoyable - well made movie - with great cast of characters."
      ],
      "confidence": 0.6,
      "polarity": "positive",
      "transferability_hint": "medium"
    },
    "emotional_resonance": {
      "value": "high",
      "evidence": [
        "hated when they killed off James the father.",
        "the last season is a struggle of sadness to watch."
      ],
      "confidence": 0.8,
      "polarity": "positive",
      "transferability_hint": "high"
    }
  },
  "additional_patterns": [],
  "summary": "The user has a strong preference for classic TV shows and family dramas, often valuing emotional resonance and character-driven storytelling. They show loyalty to specific series and creators, particularly enjoying simple narratives with a focus on enjoyment rather than high production quality."
}