{
  "user_id": "AGY4TTEXS4A3MZVTGKZT4OVAAGJQ",
  "core_patterns": {
    "genre_preference": {
      "value": "documentary, drama, comedy",
      "evidence": [
        "\"Errol Morris does it again as this documentary is really something to see.\"",
        "\"This show is awesome. Not for everyone but I found it very entertaining and it has some awesome actors.\""
      ],
      "confidence": 0.8,
      "polarity": "positive",
      "transferability_hint": "medium"
    },
    "narrative_complexity": {
      "value": "mixed",
      "evidence": [
        "\"While this could have been a little shorter it was a solid movie.\"",
        "\"Curtis Hanson is able to weaver a complex issue into a compelling drama.\""
      ],
      "confidence": 0.6,
      "polarity": "mixed",
      "transferability_hint": "medium"
    },
    "pacing_preference": {
      "value": "fast",
      "evidence": [
        "\"The pace of the dialogue is breakneck and is really impressive.\"",
        "\"This show is pretty dark it's also very good.\""
      ],
      "confidence": 0.7,
      "polarity": "positive",
      "transferability_hint": "medium"
    },
    "quality_sensitivity": {
      "value": "high",
      "evidence": [
        "\"Great cast and great job consolidating the story for the big screen.\"",
        "\"Happy to report Ridley did a fine job.\""
      ],
      "confidence": 0.8,
      "polarity": "positive",
      "transferability_hint": "high"
    },
    "brand_loyalty": {
      "value": "low",
      "evidence": [
        "\"I am big fan of Pearlman I just can't give this show a vote of confidence.\""
      ],
      "confidence": 0.3,
      "polarity": "mixed",
      "transferability_hint": "low"
    },
    "sensory_preference": {
      "value": "high",
      "evidence": [
        "\"This series was amazing. A great look at three of this countries most influential people.\"",
        "\"This was very cool. Compelling, interesting and with enough story lines to fill a Toyota Tundra.\""
      ],
      "confidence": 0.7,
      "polarity": "positive",
      "transferability_hint": "high"
    },
    "emotional_resonance": {
      "value": "high",
      "evidence": [
        "\"This should be required viewing in every high school history class.\"",
        "\"I found myself laughing out loud on several occasions.\""
      ],
      "confidence": 0.7,
      "polarity": "positive",
      "transferability_hint": "medium"
    }
  },
  "additional_patterns": [],
  "summary": "The user enjoys a mix of documentaries and dramas, appreciating strong performances and production quality. They prefer fast-paced narratives with high emotional resonance, though they show some mixed feelings towards narrative complexity and brand loyalty."
}